aliyunsdkscdn/__init__.py
aliyunsdkscdn/endpoint.py
aliyunsdkscdn/request/__init__.py
aliyunsdkscdn/request/v20171115/AddScdnDomainRequest.py
aliyunsdkscdn/request/v20171115/BatchDeleteScdnDomainConfigsRequest.py
aliyunsdkscdn/request/v20171115/BatchSetScdnDomainConfigsRequest.py
aliyunsdkscdn/request/v20171115/BatchStartScdnDomainRequest.py
aliyunsdkscdn/request/v20171115/BatchStopScdnDomainRequest.py
aliyunsdkscdn/request/v20171115/BatchUpdateScdnDomainRequest.py
aliyunsdkscdn/request/v20171115/CheckScdnServiceRequest.py
aliyunsdkscdn/request/v20171115/DeleteScdnDomainRequest.py
aliyunsdkscdn/request/v20171115/DeleteScdnSpecificConfigRequest.py
aliyunsdkscdn/request/v20171115/DescribeScdnCcInfoRequest.py
aliyunsdkscdn/request/v20171115/DescribeScdnCcQpsInfoRequest.py
aliyunsdkscdn/request/v20171115/DescribeScdnCcTopIpRequest.py
aliyunsdkscdn/request/v20171115/DescribeScdnCcTopUrlRequest.py
aliyunsdkscdn/request/v20171115/DescribeScdnCertificateDetailRequest.py
aliyunsdkscdn/request/v20171115/DescribeScdnCertificateListRequest.py
aliyunsdkscdn/request/v20171115/DescribeScdnDDoSInfoRequest.py
aliyunsdkscdn/request/v20171115/DescribeScdnDDoSTrafficInfoRequest.py
aliyunsdkscdn/request/v20171115/DescribeScdnDomainBpsDataRequest.py
aliyunsdkscdn/request/v20171115/DescribeScdnDomainCertificateInfoRequest.py
aliyunsdkscdn/request/v20171115/DescribeScdnDomainCnameRequest.py
aliyunsdkscdn/request/v20171115/DescribeScdnDomainConfigsRequest.py
aliyunsdkscdn/request/v20171115/DescribeScdnDomainDetailRequest.py
aliyunsdkscdn/request/v20171115/DescribeScdnDomainHitRateDataRequest.py
aliyunsdkscdn/request/v20171115/DescribeScdnDomainHttpCodeDataRequest.py
aliyunsdkscdn/request/v20171115/DescribeScdnDomainIspDataRequest.py
aliyunsdkscdn/request/v20171115/DescribeScdnDomainLogRequest.py
aliyunsdkscdn/request/v20171115/DescribeScdnDomainOriginBpsDataRequest.py
aliyunsdkscdn/request/v20171115/DescribeScdnDomainOriginTrafficDataRequest.py
aliyun_python_sdk_scdn-2.2.9.dist-info/LICENSE
aliyun_python_sdk_scdn-2.2.9.dist-info/METADATA
aliyun_python_sdk_scdn-2.2.9.dist-info/WHEEL
aliyun_python_sdk_scdn-2.2.9.dist-info/top_level.txt
aliyun_python_sdk_scdn-2.2.9.dist-info/RECORD
